alamoAlg/__init__.py
alamoAlg/model.py
alamoAlg-0.0.1.dist-info/METADATA
alamoAlg-0.0.1.dist-info/WHEEL
alamoAlg-0.0.1.dist-info/top_level.txt
alamoAlg-0.0.1.dist-info/RECORD
